click_app_template_demo_auto/__init__.py
click_app_template_demo_auto/__main__.py
click_app_template_demo_auto/_version.py
click_app_template_demo_auto/cli.py
click_app_template_demo_auto-0.4.0.dist-info/LICENSE
click_app_template_demo_auto-0.4.0.dist-info/METADATA
click_app_template_demo_auto-0.4.0.dist-info/WHEEL
click_app_template_demo_auto-0.4.0.dist-info/entry_points.txt
click_app_template_demo_auto-0.4.0.dist-info/top_level.txt
click_app_template_demo_auto-0.4.0.dist-info/RECORD
