Metadata-Version: 2.1
Name: click-app-template-demo-auto
Version: 0.4.0
Summary: Demonstrating https://github.com/AH-Merii/click-app
Author: AbdulHamid Merii
License: Apache-2.0
Project-URL: Homepage, https://github.com/AH-Merii/click-app-template-demo-auto
Project-URL: Changelog, https://github.com/AH-Merii/click-app-template-demo-auto/releases
Project-URL: Issues, https://github.com/AH-Merii/click-app-template-demo-auto/issues
Project-URL: CI, https://github.com/AH-Merii/click-app-template-demo-auto/actions
Classifier: License :: OSI Approved :: Apache Software License
Requires-Python: >=3.8
License-File: LICENSE
Requires-Dist: click
Provides-Extra: dev
Requires-Dist: pip-tools ; extra == 'dev'
Provides-Extra: release
Requires-Dist: python-semantic-release ==9.4.0 ; extra == 'release'
Requires-Dist: build ; extra == 'release'
Requires-Dist: setuptools-scm[toml] ; extra == 'release'
Provides-Extra: test
Requires-Dist: isort ; extra == 'test'
Requires-Dist: black ; extra == 'test'
Requires-Dist: flake8 ; extra == 'test'
Requires-Dist: ruff ; extra == 'test'
Requires-Dist: pytest ; extra == 'test'
Requires-Dist: pytest-cov ; extra == 'test'
